parol/__init__.py
parol/py.typed
parol-1.1.0.dist-info/LICENSE
parol-1.1.0.dist-info/METADATA
parol-1.1.0.dist-info/WHEEL
parol-1.1.0.dist-info/RECORD
